jyinterface/__init__.py
jyinterface/interface.py
jyinterface/common/__init__.py
jyinterface/common/common_pb2.py
jyinterface/common/common_pb2_grpc.py
jyinterface-1.2.5.dist-info/LICENSE
jyinterface-1.2.5.dist-info/METADATA
jyinterface-1.2.5.dist-info/WHEEL
jyinterface-1.2.5.dist-info/top_level.txt
jyinterface-1.2.5.dist-info/zip-safe
jyinterface-1.2.5.dist-info/RECORD
