Metadata-Version: 2.1
Name: jyinterface
Version: 1.2.5
Summary: project for trade interface
Home-page: https://github.com/jysatuo
Author: jy
Author-email: jysatuo@126.com
License: UNKNOWN
Platform: UNKNOWN
Classifier: Development Status :: 4 - Beta
Classifier: Operating System :: Microsoft
Classifier: Intended Audience :: Developers
Classifier: License :: OSI Approved :: MIT License
Classifier: Programming Language :: Python
Classifier: Programming Language :: Python :: 3
Classifier: Programming Language :: Python :: 3.5
Classifier: Programming Language :: Python :: 3.6
Classifier: Programming Language :: Python :: 3.7
Requires-Dist: numpy
Requires-Dist: ast-tools
Requires-Dist: grpcio
Requires-Dist: grpcio-tools
Requires-Dist: protobuf
